{
    "batchIndex": 3,
    "projectName": "RTCForge",
    "languages": ["typescript"],
    "batchFiles": [
        {
            "path": "packages/signaling/src/Authenticator.ts",
            "language": "typescript",
            "sizeLines": 83,
            "fileCategory": "code"
        },
        {
            "path": "packages/signaling/src/HeartbeatMonitor.ts",
            "language": "typescript",
            "sizeLines": 45,
            "fileCategory": "code"
        },
        {
            "path": "packages/signaling/src/Peer.ts",
            "language": "typescript",
            "sizeLines": 131,
            "fileCategory": "code"
        },
        {
            "path": "packages/signaling/src/RateLimiter.ts",
            "language": "typescript",
            "sizeLines": 19,
            "fileCategory": "code"
        },
        {
            "path": "packages/signaling/src/Room.ts",
            "language": "typescript",
            "sizeLines": 269,
            "fileCategory": "code"
        },
        {
            "path": "packages/signaling/src/RoomRegistry.ts",
            "language": "typescript",
            "sizeLines": 77,
            "fileCategory": "code"
        },
        {
            "path": "packages/signaling/src/RoomRouter.ts",
            "language": "typescript",
            "sizeLines": 73,
            "fileCategory": "code"
        },
        {
            "path": "packages/signaling/src/SignalingServer.ts",
            "language": "typescript",
            "sizeLines": 285,
            "fileCategory": "code"
        },
        {
            "path": "packages/signaling/src/protocol.ts",
            "language": "typescript",
            "sizeLines": 82,
            "fileCategory": "code"
        },
        {
            "path": "packages/signaling/src/types.ts",
            "language": "typescript",
            "sizeLines": 126,
            "fileCategory": "code"
        }
    ],
    "batchImportData": {
        "packages/signaling/src/Authenticator.ts": [
            "packages/core/src/index.ts",
            "packages/signaling/src/types.ts"
        ],
        "packages/signaling/src/HeartbeatMonitor.ts": [
            "packages/core/src/index.ts",
            "packages/signaling/src/Room.ts",
            "packages/signaling/src/types.ts"
        ],
        "packages/signaling/src/Peer.ts": [
            "packages/core/src/index.ts",
            "packages/signaling/src/protocol.ts",
            "packages/signaling/src/RateLimiter.ts",
            "packages/signaling/src/types.ts"
        ],
        "packages/signaling/src/RateLimiter.ts": [],
        "packages/signaling/src/Room.ts": [
            "packages/core/src/index.ts",
            "packages/signaling/src/Peer.ts",
            "packages/signaling/src/protocol.ts",
            "packages/signaling/src/types.ts"
        ],
        "packages/signaling/src/RoomRegistry.ts": [
            "packages/core/src/index.ts",
            "packages/signaling/src/Room.ts",
            "packages/signaling/src/types.ts"
        ],
        "packages/signaling/src/RoomRouter.ts": [
            "packages/core/src/index.ts",
            "packages/signaling/src/types.ts"
        ],
        "packages/signaling/src/SignalingServer.ts": [
            "packages/core/src/index.ts",
            "packages/signaling/src/Authenticator.ts",
            "packages/signaling/src/HeartbeatMonitor.ts",
            "packages/signaling/src/Peer.ts",
            "packages/signaling/src/protocol.ts",
            "packages/signaling/src/Room.ts",
            "packages/signaling/src/RoomRegistry.ts",
            "packages/signaling/src/RoomRouter.ts",
            "packages/signaling/src/types.ts"
        ],
        "packages/signaling/src/protocol.ts": [],
        "packages/signaling/src/types.ts": ["packages/core/src/index.ts"]
    },
    "neighborMap": {
        "packages/signaling/src/Authenticator.ts": [
            {
                "path": "packages/core/src/index.ts",
                "batchIndex": 1,
                "symbols": [
                    "EventEmitter",
                    "RtcForgeError",
                    "InvalidArgumentError",
                    "isRtcForgeError",
                    "noopLogger",
                    "noopMetrics",
                    "Metric",
                    "toError",
                    "Logger",
                    "MetricsCollector",
                    "MediaKind",
                    "NetworkStats",
                    "HashRing",
                    "RingNode",
                    "systemClock",
                    "ManualClock",
                    "Clock",
                    "randomId",
                    "SequentialId",
                    "IdGenerator",
                    "MemoryStateStore",
                    "StateStore",
                    "LocalMessageBus",
                    "MessageBus",
                    "Unsubscribe",
                    "noopLock",
                    "MemoryLock",
                    "Lock",
                    "MemoryMembership",
                    "Membership",
                    "NodeInfo",
                    "MembershipReconciler",
                    "MembershipReconcilerHandlers",
                    "GossipMembership",
                    "GossipNetwork",
                    "InMemoryGossipTransport",
                    "GossipTransport",
                    "GossipMessage",
                    "GossipEntry",
                    "GossipMembershipOptions"
                ]
            }
        ],
        "packages/signaling/src/HeartbeatMonitor.ts": [
            {
                "path": "packages/core/src/index.ts",
                "batchIndex": 1,
                "symbols": [
                    "EventEmitter",
                    "RtcForgeError",
                    "InvalidArgumentError",
                    "isRtcForgeError",
                    "noopLogger",
                    "noopMetrics",
                    "Metric",
                    "toError",
                    "Logger",
                    "MetricsCollector",
                    "MediaKind",
                    "NetworkStats",
                    "HashRing",
                    "RingNode",
                    "systemClock",
                    "ManualClock",
                    "Clock",
                    "randomId",
                    "SequentialId",
                    "IdGenerator",
                    "MemoryStateStore",
                    "StateStore",
                    "LocalMessageBus",
                    "MessageBus",
                    "Unsubscribe",
                    "noopLock",
                    "MemoryLock",
                    "Lock",
                    "MemoryMembership",
                    "Membership",
                    "NodeInfo",
                    "MembershipReconciler",
                    "MembershipReconcilerHandlers",
                    "GossipMembership",
                    "GossipNetwork",
                    "InMemoryGossipTransport",
                    "GossipTransport",
                    "GossipMessage",
                    "GossipEntry",
                    "GossipMembershipOptions"
                ]
            }
        ],
        "packages/signaling/src/Peer.ts": [
            {
                "path": "packages/core/src/index.ts",
                "batchIndex": 1,
                "symbols": [
                    "EventEmitter",
                    "RtcForgeError",
                    "InvalidArgumentError",
                    "isRtcForgeError",
                    "noopLogger",
                    "noopMetrics",
                    "Metric",
                    "toError",
                    "Logger",
                    "MetricsCollector",
                    "MediaKind",
                    "NetworkStats",
                    "HashRing",
                    "RingNode",
                    "systemClock",
                    "ManualClock",
                    "Clock",
                    "randomId",
                    "SequentialId",
                    "IdGenerator",
                    "MemoryStateStore",
                    "StateStore",
                    "LocalMessageBus",
                    "MessageBus",
                    "Unsubscribe",
                    "noopLock",
                    "MemoryLock",
                    "Lock",
                    "MemoryMembership",
                    "Membership",
                    "NodeInfo",
                    "MembershipReconciler",
                    "MembershipReconcilerHandlers",
                    "GossipMembership",
                    "GossipNetwork",
                    "InMemoryGossipTransport",
                    "GossipTransport",
                    "GossipMessage",
                    "GossipEntry",
                    "GossipMembershipOptions"
                ]
            }
        ],
        "packages/signaling/src/Room.ts": [
            {
                "path": "packages/core/src/index.ts",
                "batchIndex": 1,
                "symbols": [
                    "EventEmitter",
                    "RtcForgeError",
                    "InvalidArgumentError",
                    "isRtcForgeError",
                    "noopLogger",
                    "noopMetrics",
                    "Metric",
                    "toError",
                    "Logger",
                    "MetricsCollector",
                    "MediaKind",
                    "NetworkStats",
                    "HashRing",
                    "RingNode",
                    "systemClock",
                    "ManualClock",
                    "Clock",
                    "randomId",
                    "SequentialId",
                    "IdGenerator",
                    "MemoryStateStore",
                    "StateStore",
                    "LocalMessageBus",
                    "MessageBus",
                    "Unsubscribe",
                    "noopLock",
                    "MemoryLock",
                    "Lock",
                    "MemoryMembership",
                    "Membership",
                    "NodeInfo",
                    "MembershipReconciler",
                    "MembershipReconcilerHandlers",
                    "GossipMembership",
                    "GossipNetwork",
                    "InMemoryGossipTransport",
                    "GossipTransport",
                    "GossipMessage",
                    "GossipEntry",
                    "GossipMembershipOptions"
                ]
            }
        ],
        "packages/signaling/src/RoomRegistry.ts": [
            {
                "path": "packages/core/src/index.ts",
                "batchIndex": 1,
                "symbols": [
                    "EventEmitter",
                    "RtcForgeError",
                    "InvalidArgumentError",
                    "isRtcForgeError",
                    "noopLogger",
                    "noopMetrics",
                    "Metric",
                    "toError",
                    "Logger",
                    "MetricsCollector",
                    "MediaKind",
                    "NetworkStats",
                    "HashRing",
                    "RingNode",
                    "systemClock",
                    "ManualClock",
                    "Clock",
                    "randomId",
                    "SequentialId",
                    "IdGenerator",
                    "MemoryStateStore",
                    "StateStore",
                    "LocalMessageBus",
                    "MessageBus",
                    "Unsubscribe",
                    "noopLock",
                    "MemoryLock",
                    "Lock",
                    "MemoryMembership",
                    "Membership",
                    "NodeInfo",
                    "MembershipReconciler",
                    "MembershipReconcilerHandlers",
                    "GossipMembership",
                    "GossipNetwork",
                    "InMemoryGossipTransport",
                    "GossipTransport",
                    "GossipMessage",
                    "GossipEntry",
                    "GossipMembershipOptions"
                ]
            }
        ],
        "packages/signaling/src/RoomRouter.ts": [
            {
                "path": "packages/core/src/index.ts",
                "batchIndex": 1,
                "symbols": [
                    "EventEmitter",
                    "RtcForgeError",
                    "InvalidArgumentError",
                    "isRtcForgeError",
                    "noopLogger",
                    "noopMetrics",
                    "Metric",
                    "toError",
                    "Logger",
                    "MetricsCollector",
                    "MediaKind",
                    "NetworkStats",
                    "HashRing",
                    "RingNode",
                    "systemClock",
                    "ManualClock",
                    "Clock",
                    "randomId",
                    "SequentialId",
                    "IdGenerator",
                    "MemoryStateStore",
                    "StateStore",
                    "LocalMessageBus",
                    "MessageBus",
                    "Unsubscribe",
                    "noopLock",
                    "MemoryLock",
                    "Lock",
                    "MemoryMembership",
                    "Membership",
                    "NodeInfo",
                    "MembershipReconciler",
                    "MembershipReconcilerHandlers",
                    "GossipMembership",
                    "GossipNetwork",
                    "InMemoryGossipTransport",
                    "GossipTransport",
                    "GossipMessage",
                    "GossipEntry",
                    "GossipMembershipOptions"
                ]
            }
        ],
        "packages/signaling/src/SignalingServer.ts": [
            {
                "path": "packages/core/src/index.ts",
                "batchIndex": 1,
                "symbols": [
                    "EventEmitter",
                    "RtcForgeError",
                    "InvalidArgumentError",
                    "isRtcForgeError",
                    "noopLogger",
                    "noopMetrics",
                    "Metric",
                    "toError",
                    "Logger",
                    "MetricsCollector",
                    "MediaKind",
                    "NetworkStats",
                    "HashRing",
                    "RingNode",
                    "systemClock",
                    "ManualClock",
                    "Clock",
                    "randomId",
                    "SequentialId",
                    "IdGenerator",
                    "MemoryStateStore",
                    "StateStore",
                    "LocalMessageBus",
                    "MessageBus",
                    "Unsubscribe",
                    "noopLock",
                    "MemoryLock",
                    "Lock",
                    "MemoryMembership",
                    "Membership",
                    "NodeInfo",
                    "MembershipReconciler",
                    "MembershipReconcilerHandlers",
                    "GossipMembership",
                    "GossipNetwork",
                    "InMemoryGossipTransport",
                    "GossipTransport",
                    "GossipMessage",
                    "GossipEntry",
                    "GossipMembershipOptions"
                ]
            }
        ],
        "packages/signaling/src/types.ts": [
            {
                "path": "packages/core/src/index.ts",
                "batchIndex": 1,
                "symbols": [
                    "EventEmitter",
                    "RtcForgeError",
                    "InvalidArgumentError",
                    "isRtcForgeError",
                    "noopLogger",
                    "noopMetrics",
                    "Metric",
                    "toError",
                    "Logger",
                    "MetricsCollector",
                    "MediaKind",
                    "NetworkStats",
                    "HashRing",
                    "RingNode",
                    "systemClock",
                    "ManualClock",
                    "Clock",
                    "randomId",
                    "SequentialId",
                    "IdGenerator",
                    "MemoryStateStore",
                    "StateStore",
                    "LocalMessageBus",
                    "MessageBus",
                    "Unsubscribe",
                    "noopLock",
                    "MemoryLock",
                    "Lock",
                    "MemoryMembership",
                    "Membership",
                    "NodeInfo",
                    "MembershipReconciler",
                    "MembershipReconcilerHandlers",
                    "GossipMembership",
                    "GossipNetwork",
                    "InMemoryGossipTransport",
                    "GossipTransport",
                    "GossipMessage",
                    "GossipEntry",
                    "GossipMembershipOptions"
                ]
            }
        ]
    }
}
